[
  {
    "id": "p-kim-uchang",
    "name": "김우창",
    "ref": "https://www.wikidata.org/wiki/Q12498425 https://encykorea.aks.ac.kr/Article/E0010002",
    "essay_count": 30,
    "subjects": [
      "p-rilke",
      "p-yun-dongju",
      "p-jang-yonghak",
      "p-stendhal",
      "p-choi-inhun",
      "p-jung-hyunjong",
      "p-jung-jiyong",
      "p-jeong-dongju",
      "p-yi-hyoseok",
      "p-coleridge",
      "p-choe-seungho",
      "p-kim-sikwon",
      "p-yeom-sangsub",
      "p-byeon-youngro",
      "p-kim-kwanggyu",
      "p-kim-dongin",
      "p-kim-jiha",
      "p-jung-heesung",
      "p-kim-changwan",
      "p-hwang-dongkyu",
      "p-park-mokwol",
      "p-son-changsub",
      "p-kim-hyunseung",
      "p-kim-dongri",
      "p-kim-suyoung",
      "p-lawrence",
      "p-yi-chungjun",
      "p-hwang-sunwon",
      "p-poe",
      "p-ko-un",
      "p-yi-gwangsu",
      "p-oh-kyuwon",
      "p-jo-sehi",
      "p-cho-taeill",
      "p-sim-hun",
      "p-cho-jihun"
    ],
    "theorists": [
      "p-gorky",
      "p-arnold",
      "p-bettelheim",
      "p-hegel",
      "p-chernyshevsky",
      "p-sartre",
      "p-lenin",
      "p-lukacs",
      "p-poulet",
      "p-engels",
      "p-habermas",
      "p-rilke",
      "p-starobinski",
      "p-durkheim",
      "p-eliot",
      "p-valery",
      "p-dostoevsky",
      "p-arnheim",
      "p-vico",
      "p-paul-hazard",
      "p-yoo-jongho",
      "p-homer",
      "p-baek-nakchung",
      "p-dufrenne",
      "p-bergson",
      "p-freud",
      "p-plato",
      "p-bacon",
      "p-trilling",
      "p-austin",
      "p-xunzi",
      "p-descartes",
      "p-zhdanov",
      "p-kant",
      "p-zijderveld",
      "p-lacan",
      "p-platon",
      "p-leibniz",
      "p-balazs",
      "p-iser",
      "p-radek",
      "p-ian-watt",
      "p-merleau-ponty",
      "p-virgil",
      "p-dilthey",
      "p-walter-benjamin",
      "p-pak-jiwon",
      "p-marx",
      "p-heidegger",
      "p-binswanger",
      "p-kristeva",
      "p-weber",
      "p-campanella",
      "p-baek-chul",
      "p-kim-byungik",
      "p-auerbach",
      "p-raymond-williams",
      "p-popper",
      "p-whorf",
      "p-plekhanov",
      "p-sombart",
      "p-marcuse",
      "p-levi-strauss",
      "p-lubbock",
      "p-thomas-more",
      "p-whitman",
      "p-kim-jonggil"
    ]
  },
  {
    "id": "p-yu-jongho",
    "name": "유종호",
    "ref": "https://www.wikidata.org/wiki/Q12610003 http://lod.nl.go.kr/resource/KAC201106284",
    "essay_count": 17,
    "subjects": [
      "p-choe-namseon",
      "p-kim-sowol",
      "p-ju-yohan",
      "p-jeong-jiyong"
    ],
    "theorists": [
      "p-sartre",
      "p-balzac",
      "p-shelley",
      "p-taine",
      "p-gide",
      "p-swift",
      "p-hulme",
      "p-spender",
      "p-murry",
      "p-korzybski",
      "p-lubbock-percy",
      "p-day-lewis",
      "p-paulhan",
      "p-empson",
      "p-pascal",
      "p-marx",
      "p-aristotle",
      "p-shestov",
      "p-huxley",
      "p-hobbes",
      "p-nietzsche-son",
      "p-camus",
      "p-babbitt-irving",
      "p-laforge-rene",
      "p-schopenhauer",
      "p-proust",
      "p-warren",
      "p-mallarme",
      "p-valery",
      "p-flaubert",
      "p-sainte-beuve",
      "p-plato",
      "p-massis",
      "p-schleiermacher",
      "p-gourmont",
      "p-langer",
      "p-amiel",
      "p-fiedler-konrad",
      "p-nietzsche",
      "p-tyndall-william",
      "p-baudelaire",
      "p-roman-rolland",
      "p-thomas-mann",
      "p-kenneth-burke",
      "p-malinowski",
      "p-levy-bruhl",
      "p-thibaudet",
      "p-lautreamont",
      "p-brooks",
      "p-eliot",
      "p-wellek",
      "p-lawrence-dh",
      "p-freud",
      "p-hazlitt",
      "p-alberes",
      "p-auden",
      "p-chekhov",
      "p-walter-pater",
      "p-stevenson",
      "p-pound",
      "p-fraser",
      "p-benedict-ruth",
      "p-william-james",
      "p-lamb-charles",
      "p-thomas-mann-son",
      "p-herbert-read",
      "p-kafka",
      "p-russell",
      "p-fukuzawa",
      "p-henry-miller",
      "p-akutagawa",
      "p-santayana",
      "p-lowes",
      "p-gide-son",
      "p-yeats",
      "p-fromm",
      "p-moulton",
      "p-maupassant",
      "p-goethe",
      "p-stendhal-son",
      "p-richards",
      "p-maugham"
    ]
  }
]